internals/__init__.py
internals/chat.py
internals/chat_completer.py
internals/message.py
internals/prompt_loader.py
internals/status.py
internals/system.py
internals/user.py
philosopher_chat-0.0.1.dist-info/licenses/LICENSE
utils/__init__.py
utils/globals.py
philosopher_chat-0.0.1.dist-info/METADATA
philosopher_chat-0.0.1.dist-info/WHEEL
philosopher_chat-0.0.1.dist-info/top_level.txt
philosopher_chat-0.0.1.dist-info/RECORD
