Metadata-Version: 2.4
Name: philosopher-chat
Version: 0.0.1
Summary: Chat with philosophers!
Author-email: Erfan Moosavi <erfanmoosavi84@gmail.com>
License: MIT License
Project-URL: Homepage, https://github.com/pypa/sampleproject
Requires-Python: >=3.8
License-File: LICENSE
Requires-Dist: openai==1.97.1
Requires-Dist: PyYAML>=6.0
Requires-Dist: python-dotenv>=1.0.0
Dynamic: license-file
